[
{"bookname": "\u5251\u9053\u7b2c\u4e00\u4ed9", "author": "\u8427\u747e\u745c"},
{"bookname": "\u94a7\u5929\u56fe", "author": "\u7eb3\u697c\u5170"},
{"bookname": "\u6700\u5f3a\u72c2\u5175", "author": "\u70c8\u7130\u6ed4\u6ed4"},
{"bookname": "\u4e07\u52ab\u4e4b\u4e3b", "author": "\u620f\u68a6\u5e08"},
{"bookname": "\u5251\u4ed9\u5728\u6b64", "author": "\u4e71\u4e16\u72c2\u5200"},
{"bookname": "\u5dee\u4e00\u6b65\u82df\u5230\u6700\u540e", "author": "\u5341\u9636\u6d6e\u5c60"},
{"bookname": "\u5251\u6765", "author": "\u70fd\u706b\u620f\u8bf8\u4faf"},
{"bookname": "\u96ea\u9b54\u5200", "author": "\u51ac\u5f92"},
{"bookname": "\u4e00\u8bed\u7834\u5929\u673a", "author": "\u672a\u5b9a\u4e49\u516c\u5f0f"},
{"bookname": "\u4e00\u5251\u72ec\u5c0a", "author": "\u9752\u9e3e\u5cf0\u4e0a"},
{"bookname": "\u5343\u53e4\u82f1\u96c4\u5fd7", "author": "\u4e8c\u9a6c\u76d8\u69fd"},
{"bookname": "\u8f6e\u56de\u4ed9\u738b", "author": "\u7b14\u4e0b\u7075\u52a8"},
{"bookname": "\u8fb9\u6708\u6ee1\u897f\u5c71", "author": "\u5955\u8fb0\u8fb0"},
{"bookname": "\u602a\u7269\u7684\u7f8e\u597d\u751f\u6d3b", "author": "\u897f\u725b\u76ae"},
{"bookname": "\u5730\u5e54\u4e16\u754c", "author": "\u6587\u5fc3\u866b\u866b"},
{"bookname": "\u5c06\u519b\u597d\u51f6\u731b", "author": "\u66f4\u4fd7"},
{"bookname": "\u8e0f\u661f", "author": "\u968f\u6563\u98d8\u98ce"},
{"bookname": "\u4e07\u53e4\u7b2c\u4e00\u6b66\u795e", "author": "\u98ce\u72c2\u7b11"},
{"bookname": "\u81f3\u5c0a\u90aa\u5723", "author": "\u72ec\u5b64\u8001\u9053"},
{"bookname": "\u90fd\u5e02\u6253\u8138\u72c2\u4eba", "author": "\u8ff7\u8292\u4e86\u534a\u8f88\u5b50"}
]